LICENSE
README.md
dotlinker.py
setup.py
dotlinker.egg-info/PKG-INFO
dotlinker.egg-info/SOURCES.txt
dotlinker.egg-info/dependency_links.txt
dotlinker.egg-info/entry_points.txt
dotlinker.egg-info/requires.txt
dotlinker.egg-info/top_level.txt