Metadata-Version: 1.0
Name: dotlinker
Version: 0.1.2
Summary: Links dotfiles
Home-page: https://github.com/jondot/dotlinker
Author: Dotan Nahum
Author-email: jondotan@gmail.com
License: Copyright (c) 2012, Kenneth Reitz
